{
  "data": {
    "episodes": [
      {
        "title": "影视飓风TIM×罗永浩！用影像打开世界的梦想家",
        "podcastID": "26bebc908962ea66ff15093e11d89ca9",
        "podcastName": "罗永浩的十字路口",
        "logoURL": "https://is1-ssl.mzstatic.com/image/thumb/Podcasts221/v4/79/45/99/794599ee-b368-ad32-08c1-10fb8da1ab96/mza_4122156040194880124.png/100x100bb.jpg",
        "link": "https://www.xiaoyuzhoufm.com/episode/68e74f521bef327f3d7ddcd7",
        "playCount": 228497,
        "commentCount": 1019,
        "subscription": 32152,
        "duration": 172,
        "postTime": "2025-10-10T04:00:00.000Z",
        "primaryGenreName": "科技",
        "totalEpisodesCount": 4,
        "openRate": 7.1067740731525255,
        "lastReleaseDateDayCount": 5.646167071759259
      },
      {
        "title": "vol.09 预制菜风波！美味和效率，谁去谁留？",
        "podcastID": "e2b8133a07a0e86a99f1698443bc548f",
        "podcastName": "米地研究所",
        "logoURL": "https://xyzrank.justinbot.com/Fma5qBGN9N9mBQRbFEYeJQretauJ.jpg@small",
        "link": "https://www.xiaoyuzhoufm.com/episode/68df81a68bf86095c5aa5c85",
        "playCount": 9252,
        "commentCount": 332,
        "subscription": 6866,
        "duration": 126,
        "postTime": "2025-10-03T12:00:00.000Z",
        "primaryGenreName": "",
        "totalEpisodesCount": 9,
        "openRate": 1.3475094669385377,
        "lastReleaseDateDayCount": 12.312833738425926
      },
      {
        "title": "8. 我用什么把你留住",
        "podcastID": "b843ea142e584a80b9f72a015a07379d",
        "podcastName": "公道五路",
        "logoURL": "https://is1-ssl.mzstatic.com/image/thumb/Podcasts221/v4/d7/84/48/d784489c-d33d-2fd5-9480-10a0f8286d1a/mza_4996144779968586965.jpg/100x100bb.jpg",
        "link": "https://www.xiaoyuzhoufm.com/episode/68ddc8ef8e321a0d6fa68b0f",
        "playCount": 8716,
        "commentCount": 202,
        "subscription": 2952,
        "duration": 59,
        "postTime": "2025-10-02T01:01:19.333Z",
        "primaryGenreName": "犯罪纪实",
        "totalEpisodesCount": 14,
        "openRate": 2.9525745257452574,
        "lastReleaseDateDayCount": 13.77024886574074
      },
      {
        "title": "傅月庵：纸本书出版市场的崩坏速度远超预期",
        "podcastID": "a02cbc258b64978db3abd764627469d5",
        "podcastName": "读药丸",
        "logoURL": "https://xyzrank.justinbot.com/Fl_SpwnXGeS7Evx5VJuCaOunjGyD.jpg@small",
        "link": "https://www.xiaoyuzhoufm.com/episode/68ecd142224325ea70040ff5",
        "playCount": 5463,
        "commentCount": 32,
        "subscription": 3977,
        "duration": 45,
        "postTime": "2025-10-13T23:00:00.000Z",
        "primaryGenreName": "",
        "totalEpisodesCount": 10,
        "openRate": 1.3736484787528287,
        "lastReleaseDateDayCount": 1.8545004050925926
      },
      {
        "title": "vol.10 当一个内向的人渴望与周围产生链接",
        "podcastID": "04089fd91e24c03cc0d95780adf244e5",
        "podcastName": "杜素娟的会客厅",
        "logoURL": "https://xyzrank.justinbot.com/FknKoeMSuNP4MS7Xeaj-dGnrGBuo.jpg@small",
        "link": "https://www.xiaoyuzhoufm.com/episode/68e76f4e1bef327f3d849e12",
        "playCount": 4877,
        "commentCount": 9,
        "subscription": 15914,
        "duration": 66,
        "postTime": "2025-10-09T08:36:45.313Z",
        "primaryGenreName": "",
        "totalEpisodesCount": 8,
        "openRate": 0.30645972100037705,
        "lastReleaseDateDayCount": 6.453975949074074
      },
      {
        "title": "10. 从脱口秀到技能五子棋，讨好大众容易，冒犯自己很难",
        "podcastID": "c14b9090cfed18267185a060b35cef8a",
        "podcastName": "热可可",
        "logoURL": "https://is1-ssl.mzstatic.com/image/thumb/Podcasts221/v4/99/06/fb/9906fb75-8c69-aa8a-f8a5-2ed559848ede/mza_10695213421880127814.jpg/100x100bb.jpg",
        "link": "https://www.xiaoyuzhoufm.com/episode/68eb4365525f51df38e44e15",
        "playCount": 4706,
        "commentCount": 120,
        "subscription": 21035,
        "duration": 53,
        "postTime": "2025-10-13T00:00:00.000Z",
        "primaryGenreName": "社会与文化",
        "totalEpisodesCount": 20,
        "openRate": 0.2237223674827668,
        "lastReleaseDateDayCount": 2.812833738425926
      },
      {
        "title": "丘山：摄影、留学、项目管理、作品与阐释，我们该如何走入当代艺术？",
        "podcastID": "cb9f0936af12aa439be676b0db98bf21",
        "podcastName": "蜉蝣天地 Meanders",
        "logoURL": "https://is1-ssl.mzstatic.com/image/thumb/Podcasts211/v4/5a/ef/32/5aef3243-5cd8-8f50-1f23-9841b513bcf6/mza_12924067301715234166.jpg/100x100bb.jpg",
        "link": "https://www.xiaoyuzhoufm.com/episode/68e299328bf86095c5e70ded",
        "playCount": 2116,
        "commentCount": 34,
        "subscription": 8506,
        "duration": 164,
        "postTime": "2025-10-06T04:00:00.000Z",
        "primaryGenreName": "休闲",
        "totalEpisodesCount": 18,
        "openRate": 0.24876557723959558,
        "lastReleaseDateDayCount": 9.64616707175926
      },
      {
        "title": "13 清醒女孩搞钱实录：18岁赚到百万，20岁离婚创业，我的人生我做主！",
        "podcastID": "d8d2327400bea578f96a235b2439424c",
        "podcastName": "谈钱说爱deep talk",
        "logoURL": "https://xyzrank.justinbot.com/Fob8eLfOF9d39EndY2E2RS6SQhml.jpg@small",
        "link": "https://www.xiaoyuzhoufm.com/episode/68d80fd8b4befcf73036698a",
        "playCount": 1903,
        "commentCount": 15,
        "subscription": 706,
        "duration": 67,
        "postTime": "2025-10-04T16:00:00.000Z",
        "primaryGenreName": "",
        "totalEpisodesCount": 7,
        "openRate": 2.6954674220963173,
        "lastReleaseDateDayCount": 11.14616707175926
      }
    ],
    "medianValues": {
      "playCount": 5170,
      "commentCount": 77,
      "interactiveRate": 0.011975172024671025,
      "openRate": 1.3605789728456832,
      "duration": 66.5,
      "lastReleaseDateDayCount": 8.050071510416668
    }
  },
  "type": 3
}